{"product":{"id":7487927156960,"title":"Brunch Bear iPhone Case with Charm","body_html":"\u003cp data-mce-fragment=\"1\"\u003eThis\u00a0cartoon design has an adorable\u00a0bear design\u00a0with a wonderful bear charm to keep you company. Protect your iPhone with this kawaii buddy, and\u00a0feel warmth and happiness each time you pick it up!\u003c\/p\u003e\n\u003cp data-mce-fragment=\"1\"\u003e\u003cstrong data-mce-fragment=\"1\"\u003eDescription:\u003c\/strong\u003e\u003c\/p\u003e\n\u003cul class=\"cDetailUl\" data-mce-fragment=\"1\"\u003e\n\u003cli data-mce-fragment=\"1\"\u003eSoft Silicone Cover Case with Hanging Charm\u003c\/li\u003e\n\u003cli data-mce-fragment=\"1\"\u003eCompatible Brand: Apple iPhones\u003cbr data-mce-fragment=\"1\"\u003e\n\u003c\/li\u003e\n\u003cli data-mce-fragment=\"1\"\u003eFunction: Anti-knock. Dirt-resistant\u003c\/li\u003e\n\u003cli data-mce-fragment=\"1\"\u003eDesign:\u00a0Brown Bear\u003c\/li\u003e\n\u003cli data-mce-fragment=\"1\"\u003eColor:\u00a0Beige, Brown\u003c\/li\u003e\n\u003c\/ul\u003e\n\u003cp data-mce-fragment=\"1\"\u003eA durable flexible case that grips around the edges of your phone.\u003c\/p\u003e\n\u003cp data-mce-fragment=\"1\"\u003eMake sure you select the correct iPhone when ordering and as you can probably guess the phone itself is not sold with this case.\u003c\/p\u003e","vendor":"Accessories","product_type":"Accessories","created_at":"2021-12-08T02:52:49+00:00","handle":"cookie-bear-iphone-case-with-charm","updated_at":"2024-02-11T07:49:30+00:00","published_at":"2021-12-08T03:25:11+00:00","template_suffix":"","published_scope":"web","tags":"Bear, Bears, Brown, case, cases, iphone, iPhone 13, iPhone Case, iPhone cases, Mobile Case, Mobile Cases, Phone Case, Phone Cases","variants":[{"id":42172741026016,"product_id":7487927156960,"title":"Brown \/ iPhone 7","price":"19.99","sku":"49266049-for-iphone-7-b-with-pendant","position":1,"compare_at_price":"25.00","fulfillment_service":"dsers-fulfillment-service","inventory_management":"shopify","option1":"Brown","option2":"iPhone 7","option3":null,"created_at":"2021-12-08T02:52:50+00:00","updated_at":"2024-02-11T07:49:30+00:00","taxable":false,"barcode":null,"grams":0,"image_id":36736882966752,"weight":0.0,"weight_unit":"g","requires_shipping":true},{"id":42172741058784,"product_id":7487927156960,"title":"Brown \/ iPhone 7 Plus","price":"19.99","sku":"49266049-for-iphone-7-plus-b-with-pendant","position":2,"compare_at_price":"25.00","fulfillment_service":"dsers-fulfillment-service","inventory_management":"shopify","option1":"Brown","option2":"iPhone 7 Plus","option3":null,"created_at":"2021-12-08T02:52:50+00:00","updated_at":"2024-02-11T07:49:30+00:00","taxable":false,"barcode":null,"grams":0,"image_id":36736882966752,"weight":0.0,"weight_unit":"g","requires_shipping":true},{"id":42172741320928,"product_id":7487927156960,"title":"Brown \/ iPhone 8","price":"19.99","sku":"49266049-for-iphone-8-b-with-pendant","position":3,"compare_at_price":"25.00","fulfillment_service":"dsers-fulfillment-service","inventory_management":"shopify","option1":"Brown","option2":"iPhone 8","option3":null,"created_at":"2021-12-08T02:52:50+00:00","updated_at":"2024-02-11T07:49:30+00:00","taxable":false,"barcode":null,"grams":0,"image_id":36736882966752,"weight":0.0,"weight_unit":"g","requires_shipping":true},{"id":42172741353696,"product_id":7487927156960,"title":"Brown \/ iPhone 8 Plus","price":"19.99","sku":"49266049-for-iphone-8-plus-b-with-pendant","position":4,"compare_at_price":"25.00","fulfillment_service":"dsers-fulfillment-service","inventory_management":"shopify","option1":"Brown","option2":"iPhone 8 Plus","option3":null,"created_at":"2021-12-08T02:52:50+00:00","updated_at":"2024-02-11T07:49:30+00:00","taxable":false,"barcode":null,"grams":0,"image_id":36736882966752,"weight":0.0,"weight_unit":"g","requires_shipping":true},{"id":42172741386464,"product_id":7487927156960,"title":"Brown \/ iPhone X","price":"19.99","sku":"49266049-for-iphone-x-b-with-pendant","position":5,"compare_at_price":"25.00","fulfillment_service":"dsers-fulfillment-service","inventory_management":"shopify","option1":"Brown","option2":"iPhone X","option3":null,"created_at":"2021-12-08T02:52:50+00:00","updated_at":"2024-02-11T07:49:30+00:00","taxable":false,"barcode":null,"grams":0,"image_id":36736882966752,"weight":0.0,"weight_unit":"g","requires_shipping":true},{"id":42172741222624,"product_id":7487927156960,"title":"Brown \/ iPhone XR","price":"19.99","sku":"49266049-for-iphone-xr-b-with-pendant","position":6,"compare_at_price":"25.00","fulfillment_service":"dsers-fulfillment-service","inventory_management":"shopify","option1":"Brown","option2":"iPhone XR","option3":null,"created_at":"2021-12-08T02:52:50+00:00","updated_at":"2024-02-11T07:49:30+00:00","taxable":false,"barcode":null,"grams":0,"image_id":36736882966752,"weight":0.0,"weight_unit":"g","requires_shipping":true},{"id":42172741419232,"product_id":7487927156960,"title":"Brown \/ iPhone XS","price":"19.99","sku":"49266049-for-iphone-xs-b-with-pendant","position":7,"compare_at_price":"25.00","fulfillment_service":"dsers-fulfillment-service","inventory_management":"shopify","option1":"Brown","option2":"iPhone XS","option3":null,"created_at":"2021-12-08T02:52:50+00:00","updated_at":"2024-02-11T07:49:30+00:00","taxable":false,"barcode":null,"grams":0,"image_id":36736882966752,"weight":0.0,"weight_unit":"g","requires_shipping":true},{"id":42172741255392,"product_id":7487927156960,"title":"Brown \/ iPhone 11","price":"19.99","sku":"49266049-for-iphone-11-b-with-pendant","position":8,"compare_at_price":"25.00","fulfillment_service":"dsers-fulfillment-service","inventory_management":"shopify","option1":"Brown","option2":"iPhone 11","option3":null,"created_at":"2021-12-08T02:52:50+00:00","updated_at":"2024-02-11T07:49:30+00:00","taxable":false,"barcode":null,"grams":0,"image_id":36736882966752,"weight":0.0,"weight_unit":"g","requires_shipping":true},{"id":42172741288160,"product_id":7487927156960,"title":"Brown \/ iPhone 11 Pro","price":"19.99","sku":"49266049-for-iphone-11-pro-b-with-pendant","position":9,"compare_at_price":"25.00","fulfillment_service":"dsers-fulfillment-service","inventory_management":"shopify","option1":"Brown","option2":"iPhone 11 Pro","option3":null,"created_at":"2021-12-08T02:52:50+00:00","updated_at":"2024-02-11T07:49:30+00:00","taxable":false,"barcode":null,"grams":0,"image_id":36736882966752,"weight":0.0,"weight_unit":"g","requires_shipping":true},{"id":42172740403424,"product_id":7487927156960,"title":"Brown \/ iPhone 11 Pro Max","price":"19.99","sku":"49266049-for-iphone-11promax-b-with-pendant","position":10,"compare_at_price":"25.00","fulfillment_service":"dsers-fulfillment-service","inventory_management":"shopify","option1":"Brown","option2":"iPhone 11 Pro Max","option3":null,"created_at":"2021-12-08T02:52:49+00:00","updated_at":"2024-02-11T07:49:30+00:00","taxable":false,"barcode":null,"grams":0,"image_id":36736882966752,"weight":0.0,"weight_unit":"g","requires_shipping":true},{"id":42172740436192,"product_id":7487927156960,"title":"Brown \/ iPhone 12","price":"19.99","sku":"49266049-for-iphone-12-b-with-pendant","position":11,"compare_at_price":"25.00","fulfillment_service":"dsers-fulfillment-service","inventory_management":"shopify","option1":"Brown","option2":"iPhone 12","option3":null,"created_at":"2021-12-08T02:52:49+00:00","updated_at":"2024-02-11T07:49:30+00:00","taxable":false,"barcode":null,"grams":0,"image_id":36736882966752,"weight":0.0,"weight_unit":"g","requires_shipping":true},{"id":42172740468960,"product_id":7487927156960,"title":"Brown \/ iPhone 12 Pro","price":"19.99","sku":"49266049-for-iphone-12-pro-b-with-pendant","position":12,"compare_at_price":"25.00","fulfillment_service":"dsers-fulfillment-service","inventory_management":"shopify","option1":"Brown","option2":"iPhone 12 Pro","option3":null,"created_at":"2021-12-08T02:52:49+00:00","updated_at":"2024-02-11T07:49:30+00:00","taxable":false,"barcode":null,"grams":0,"image_id":36736882966752,"weight":0.0,"weight_unit":"g","requires_shipping":true},{"id":42172740272352,"product_id":7487927156960,"title":"Brown \/ iPhone 12 Pro Max","price":"19.99","sku":"49266049-for-iphone-12promax-b-with-pendant","position":13,"compare_at_price":"25.00","fulfillment_service":"dsers-fulfillment-service","inventory_management":"shopify","option1":"Brown","option2":"iPhone 12 Pro Max","option3":null,"created_at":"2021-12-08T02:52:49+00:00","updated_at":"2024-02-11T07:49:30+00:00","taxable":false,"barcode":null,"grams":0,"image_id":36736882966752,"weight":0.0,"weight_unit":"g","requires_shipping":true},{"id":42172740305120,"product_id":7487927156960,"title":"Brown \/ iPhone 12 Mini","price":"19.99","sku":"49266049-for-iphone-12mini-b-with-pendant","position":14,"compare_at_price":"25.00","fulfillment_service":"dsers-fulfillment-service","inventory_management":"shopify","option1":"Brown","option2":"iPhone 12 Mini","option3":null,"created_at":"2021-12-08T02:52:49+00:00","updated_at":"2024-02-11T07:49:30+00:00","taxable":false,"barcode":null,"grams":0,"image_id":36736882966752,"weight":0.0,"weight_unit":"g","requires_shipping":true},{"id":42172740337888,"product_id":7487927156960,"title":"Brown \/ iPhone 13","price":"19.99","sku":"49266049-for-iphone-13-b-with-pendant","position":15,"compare_at_price":"25.00","fulfillment_service":"dsers-fulfillment-service","inventory_management":"shopify","option1":"Brown","option2":"iPhone 13","option3":null,"created_at":"2021-12-08T02:52:49+00:00","updated_at":"2024-02-11T07:49:30+00:00","taxable":false,"barcode":null,"grams":0,"image_id":36736882966752,"weight":0.0,"weight_unit":"g","requires_shipping":true},{"id":42172740370656,"product_id":7487927156960,"title":"Brown \/ iPhone 13 Pro","price":"19.99","sku":"49266049-for-iphone-13-pro-b-with-pendant","position":16,"compare_at_price":"25.00","fulfillment_service":"dsers-fulfillment-service","inventory_management":"shopify","option1":"Brown","option2":"iPhone 13 Pro","option3":null,"created_at":"2021-12-08T02:52:49+00:00","updated_at":"2024-02-11T07:49:30+00:00","taxable":false,"barcode":null,"grams":0,"image_id":36736882966752,"weight":0.0,"weight_unit":"g","requires_shipping":true},{"id":42172740501728,"product_id":7487927156960,"title":"Brown \/ iPhone 13 Pro Max","price":"19.99","sku":"49266049-for-iphone-13promax-b-with-pendant","position":17,"compare_at_price":"25.00","fulfillment_service":"dsers-fulfillment-service","inventory_management":"shopify","option1":"Brown","option2":"iPhone 13 Pro Max","option3":null,"created_at":"2021-12-08T02:52:49+00:00","updated_at":"2024-02-11T07:49:30+00:00","taxable":false,"barcode":null,"grams":0,"image_id":36736882966752,"weight":0.0,"weight_unit":"g","requires_shipping":true},{"id":43911485817056,"product_id":7487927156960,"title":"Brown \/ iPhone 14","price":"19.99","sku":"49266049-for-iphone-14-b-with-pendant","position":18,"compare_at_price":"25.00","fulfillment_service":"dsers-fulfillment-service","inventory_management":"shopify","option1":"Brown","option2":"iPhone 14","option3":null,"created_at":"2023-03-07T23:37:03+00:00","updated_at":"2024-02-11T07:49:30+00:00","taxable":false,"barcode":"","grams":0,"image_id":36736882966752,"weight":0.0,"weight_unit":"g","requires_shipping":true},{"id":43911485882592,"product_id":7487927156960,"title":"Brown \/ iPhone 14 Plus","price":"19.99","sku":"49266049-for-iphone-14plus-b-with-pendant","position":19,"compare_at_price":"25.00","fulfillment_service":"dsers-fulfillment-service","inventory_management":"shopify","option1":"Brown","option2":"iPhone 14 Plus","option3":null,"created_at":"2023-03-07T23:37:03+00:00","updated_at":"2024-02-11T07:49:30+00:00","taxable":false,"barcode":"","grams":0,"image_id":36736882966752,"weight":0.0,"weight_unit":"g","requires_shipping":true},{"id":43911485915360,"product_id":7487927156960,"title":"Brown \/ iPhone 14 Pro","price":"19.99","sku":"49266049-for-iphone-14pro-b-with-pendant","position":20,"compare_at_price":"25.00","fulfillment_service":"dsers-fulfillment-service","inventory_management":"shopify","option1":"Brown","option2":"iPhone 14 Pro","option3":null,"created_at":"2023-03-07T23:37:03+00:00","updated_at":"2024-02-11T07:49:30+00:00","taxable":false,"barcode":"","grams":0,"image_id":36736882966752,"weight":0.0,"weight_unit":"g","requires_shipping":true},{"id":43911485948128,"product_id":7487927156960,"title":"Brown \/ iPhone 14 Pro Max","price":"19.99","sku":"49266049-for-iphone-14promax-b-with-pendant","position":21,"compare_at_price":"25.00","fulfillment_service":"dsers-fulfillment-service","inventory_management":"shopify","option1":"Brown","option2":"iPhone 14 Pro Max","option3":null,"created_at":"2023-03-07T23:37:03+00:00","updated_at":"2024-02-11T07:49:30+00:00","taxable":false,"barcode":"","grams":0,"image_id":36736882966752,"weight":0.0,"weight_unit":"g","requires_shipping":true},{"id":42172740665568,"product_id":7487927156960,"title":"Beige \/ iPhone 7","price":"19.99","sku":"49266049-for-iphone-7-a-with-pendant","position":22,"compare_at_price":"25.00","fulfillment_service":"dsers-fulfillment-service","inventory_management":"shopify","option1":"Beige","option2":"iPhone 7","option3":null,"created_at":"2021-12-08T02:52:50+00:00","updated_at":"2024-02-11T07:49:30+00:00","taxable":false,"barcode":null,"grams":0,"image_id":36737023607008,"weight":0.0,"weight_unit":"g","requires_shipping":true},{"id":42172740534496,"product_id":7487927156960,"title":"Beige \/ iPhone 7 Plus","price":"19.99","sku":"49266049-for-iphone-7-plus-a-with-pendant","position":23,"compare_at_price":"25.00","fulfillment_service":"dsers-fulfillment-service","inventory_management":"shopify","option1":"Beige","option2":"iPhone 7 Plus","option3":null,"created_at":"2021-12-08T02:52:50+00:00","updated_at":"2024-02-11T07:49:30+00:00","taxable":false,"barcode":null,"grams":0,"image_id":36737023607008,"weight":0.0,"weight_unit":"g","requires_shipping":true},{"id":42172740567264,"product_id":7487927156960,"title":"Beige \/ iPhone 8","price":"19.99","sku":"49266049-for-iphone-8-a-with-pendant","position":24,"compare_at_price":"25.00","fulfillment_service":"dsers-fulfillment-service","inventory_management":"shopify","option1":"Beige","option2":"iPhone 8","option3":null,"created_at":"2021-12-08T02:52:50+00:00","updated_at":"2024-02-11T07:49:30+00:00","taxable":false,"barcode":null,"grams":0,"image_id":36737023607008,"weight":0.0,"weight_unit":"g","requires_shipping":true},{"id":42172740600032,"product_id":7487927156960,"title":"Beige \/ iPhone 8 Plus","price":"19.99","sku":"49266049-for-iphone-8-plus-a-with-pendant","position":25,"compare_at_price":"25.00","fulfillment_service":"dsers-fulfillment-service","inventory_management":"shopify","option1":"Beige","option2":"iPhone 8 Plus","option3":null,"created_at":"2021-12-08T02:52:50+00:00","updated_at":"2024-02-11T07:49:30+00:00","taxable":false,"barcode":null,"grams":0,"image_id":36737023607008,"weight":0.0,"weight_unit":"g","requires_shipping":true},{"id":42172740632800,"product_id":7487927156960,"title":"Beige \/ iPhone X","price":"19.99","sku":"49266049-for-iphone-x-a-with-pendant","position":26,"compare_at_price":"25.00","fulfillment_service":"dsers-fulfillment-service","inventory_management":"shopify","option1":"Beige","option2":"iPhone X","option3":null,"created_at":"2021-12-08T02:52:50+00:00","updated_at":"2024-02-11T07:49:30+00:00","taxable":false,"barcode":null,"grams":0,"image_id":36737023607008,"weight":0.0,"weight_unit":"g","requires_shipping":true},{"id":42172740894944,"product_id":7487927156960,"title":"Beige \/ iPhone XR","price":"19.99","sku":"49266049-for-iphone-xr-a-with-pendant","position":27,"compare_at_price":"25.00","fulfillment_service":"dsers-fulfillment-service","inventory_management":"shopify","option1":"Beige","option2":"iPhone XR","option3":null,"created_at":"2021-12-08T02:52:50+00:00","updated_at":"2024-02-11T07:49:30+00:00","taxable":false,"barcode":null,"grams":0,"image_id":36737023607008,"weight":0.0,"weight_unit":"g","requires_shipping":true},{"id":42172740829408,"product_id":7487927156960,"title":"Beige \/ iPhone XS","price":"19.99","sku":"49266049-for-iphone-xs-a-with-pendant","position":28,"compare_at_price":"25.00","fulfillment_service":"dsers-fulfillment-service","inventory_management":"shopify","option1":"Beige","option2":"iPhone XS","option3":null,"created_at":"2021-12-08T02:52:50+00:00","updated_at":"2024-02-11T07:49:30+00:00","taxable":false,"barcode":null,"grams":0,"image_id":36737023607008,"weight":0.0,"weight_unit":"g","requires_shipping":true},{"id":42172740927712,"product_id":7487927156960,"title":"Beige \/ iPhone 11","price":"19.99","sku":"49266049-for-iphone-11-a-with-pendant","position":29,"compare_at_price":"25.00","fulfillment_service":"dsers-fulfillment-service","inventory_management":"shopify","option1":"Beige","option2":"iPhone 11","option3":null,"created_at":"2021-12-08T02:52:50+00:00","updated_at":"2024-02-11T07:49:30+00:00","taxable":false,"barcode":null,"grams":0,"image_id":36737023607008,"weight":0.0,"weight_unit":"g","requires_shipping":true},{"id":42172740698336,"product_id":7487927156960,"title":"Beige \/ iPhone 11 Pro","price":"19.99","sku":"49266049-for-iphone-11-pro-a-with-pendant","position":30,"compare_at_price":"25.00","fulfillment_service":"dsers-fulfillment-service","inventory_management":"shopify","option1":"Beige","option2":"iPhone 11 Pro","option3":null,"created_at":"2021-12-08T02:52:50+00:00","updated_at":"2024-02-11T07:49:30+00:00","taxable":false,"barcode":null,"grams":0,"image_id":36737023607008,"weight":0.0,"weight_unit":"g","requires_shipping":true},{"id":42172740731104,"product_id":7487927156960,"title":"Beige \/ iPhone 11 Pro Max","price":"19.99","sku":"49266049-for-iphone-11promax-a-with-pendant","position":31,"compare_at_price":"25.00","fulfillment_service":"dsers-fulfillment-service","inventory_management":"shopify","option1":"Beige","option2":"iPhone 11 Pro Max","option3":null,"created_at":"2021-12-08T02:52:50+00:00","updated_at":"2024-02-11T07:49:30+00:00","taxable":false,"barcode":null,"grams":0,"image_id":36737023607008,"weight":0.0,"weight_unit":"g","requires_shipping":true},{"id":42172740763872,"product_id":7487927156960,"title":"Beige \/ iPhone 12","price":"19.99","sku":"49266049-for-iphone-12-a-with-pendant","position":32,"compare_at_price":"25.00","fulfillment_service":"dsers-fulfillment-service","inventory_management":"shopify","option1":"Beige","option2":"iPhone 12","option3":null,"created_at":"2021-12-08T02:52:50+00:00","updated_at":"2024-02-11T07:49:30+00:00","taxable":false,"barcode":null,"grams":0,"image_id":36737023607008,"weight":0.0,"weight_unit":"g","requires_shipping":true},{"id":42172741091552,"product_id":7487927156960,"title":"Beige \/ iPhone 12 Pro","price":"19.99","sku":"49266049-for-iphone-12-pro-a-with-pendant","position":33,"compare_at_price":"25.00","fulfillment_service":"dsers-fulfillment-service","inventory_management":"shopify","option1":"Beige","option2":"iPhone 12 Pro","option3":null,"created_at":"2021-12-08T02:52:50+00:00","updated_at":"2024-02-11T07:49:30+00:00","taxable":false,"barcode":null,"grams":0,"image_id":36737023607008,"weight":0.0,"weight_unit":"g","requires_shipping":true},{"id":42172741124320,"product_id":7487927156960,"title":"Beige \/ iPhone 12 Pro Max","price":"19.99","sku":"49266049-for-iphone-12promax-a-with-pendant","position":34,"compare_at_price":"25.00","fulfillment_service":"dsers-fulfillment-service","inventory_management":"shopify","option1":"Beige","option2":"iPhone 12 Pro Max","option3":null,"created_at":"2021-12-08T02:52:50+00:00","updated_at":"2024-02-11T07:49:30+00:00","taxable":false,"barcode":null,"grams":0,"image_id":36737023607008,"weight":0.0,"weight_unit":"g","requires_shipping":true},{"id":42172741157088,"product_id":7487927156960,"title":"Beige \/ iPhone 12 Mini","price":"19.99","sku":"49266049-for-iphone-12mini-a-with-pendant","position":35,"compare_at_price":"25.00","fulfillment_service":"dsers-fulfillment-service","inventory_management":"shopify","option1":"Beige","option2":"iPhone 12 Mini","option3":null,"created_at":"2021-12-08T02:52:50+00:00","updated_at":"2024-02-11T07:49:30+00:00","taxable":false,"barcode":null,"grams":0,"image_id":36737023607008,"weight":0.0,"weight_unit":"g","requires_shipping":true},{"id":42172741189856,"product_id":7487927156960,"title":"Beige \/ iPhone 13","price":"19.99","sku":"49266049-for-iphone-13-a-with-pendant","position":36,"compare_at_price":"25.00","fulfillment_service":"dsers-fulfillment-service","inventory_management":"shopify","option1":"Beige","option2":"iPhone 13","option3":null,"created_at":"2021-12-08T02:52:50+00:00","updated_at":"2024-02-11T07:49:30+00:00","taxable":false,"barcode":null,"grams":0,"image_id":36737023607008,"weight":0.0,"weight_unit":"g","requires_shipping":true},{"id":42172740960480,"product_id":7487927156960,"title":"Beige \/ iPhone 13 Pro","price":"19.99","sku":"49266049-for-iphone-13-pro-a-with-pendant","position":37,"compare_at_price":"25.00","fulfillment_service":"dsers-fulfillment-service","inventory_management":"shopify","option1":"Beige","option2":"iPhone 13 Pro","option3":null,"created_at":"2021-12-08T02:52:50+00:00","updated_at":"2024-02-11T07:49:30+00:00","taxable":false,"barcode":null,"grams":0,"image_id":36737023607008,"weight":0.0,"weight_unit":"g","requires_shipping":true},{"id":42172740993248,"product_id":7487927156960,"title":"Beige \/ iPhone 13 Pro Max","price":"19.99","sku":"49266049-for-iphone-13promax-a-with-pendant","position":38,"compare_at_price":"25.00","fulfillment_service":"dsers-fulfillment-service","inventory_management":"shopify","option1":"Beige","option2":"iPhone 13 Pro Max","option3":null,"created_at":"2021-12-08T02:52:50+00:00","updated_at":"2024-02-11T07:49:30+00:00","taxable":false,"barcode":null,"grams":0,"image_id":36737023607008,"weight":0.0,"weight_unit":"g","requires_shipping":true},{"id":43911485980896,"product_id":7487927156960,"title":"Beige \/ iPhone 14","price":"19.99","sku":"49266049-for-iphone-14-a-with-pendant","position":39,"compare_at_price":"25.00","fulfillment_service":"dsers-fulfillment-service","inventory_management":"shopify","option1":"Beige","option2":"iPhone 14","option3":null,"created_at":"2023-03-07T23:37:03+00:00","updated_at":"2024-02-11T07:49:30+00:00","taxable":false,"barcode":"","grams":0,"image_id":36737023607008,"weight":0.0,"weight_unit":"g","requires_shipping":true},{"id":43911486013664,"product_id":7487927156960,"title":"Beige \/ iPhone 14 Plus","price":"19.99","sku":"49266049-for-iphone-14plus-a-with-pendant","position":40,"compare_at_price":"25.00","fulfillment_service":"dsers-fulfillment-service","inventory_management":"shopify","option1":"Beige","option2":"iPhone 14 Plus","option3":null,"created_at":"2023-03-07T23:37:03+00:00","updated_at":"2024-02-11T07:49:30+00:00","taxable":false,"barcode":"","grams":0,"image_id":36737023607008,"weight":0.0,"weight_unit":"g","requires_shipping":true},{"id":43911486046432,"product_id":7487927156960,"title":"Beige \/ iPhone 14 Pro","price":"19.99","sku":"49266049-for-iphone-14pro-a-with-pendant","position":41,"compare_at_price":"25.00","fulfillment_service":"dsers-fulfillment-service","inventory_management":"shopify","option1":"Beige","option2":"iPhone 14 Pro","option3":null,"created_at":"2023-03-07T23:37:03+00:00","updated_at":"2024-02-11T07:49:30+00:00","taxable":false,"barcode":"","grams":0,"image_id":36737023607008,"weight":0.0,"weight_unit":"g","requires_shipping":true},{"id":43911486079200,"product_id":7487927156960,"title":"Beige \/ iPhone 14 Pro Max","price":"19.99","sku":"49266049-for-iphone-14promax-a-with-pendant","position":42,"compare_at_price":"25.00","fulfillment_service":"dsers-fulfillment-service","inventory_management":"shopify","option1":"Beige","option2":"iPhone 14 Pro Max","option3":null,"created_at":"2023-03-07T23:37:03+00:00","updated_at":"2024-02-11T07:49:30+00:00","taxable":false,"barcode":"","grams":0,"image_id":36737023607008,"weight":0.0,"weight_unit":"g","requires_shipping":true}],"options":[{"id":9528013160672,"product_id":7487927156960,"name":"Colour","position":1,"values":["Brown","Beige"]},{"id":9528013193440,"product_id":7487927156960,"name":"Model","position":2,"values":["iPhone 7","iPhone 7 Plus","iPhone 8","iPhone 8 Plus","iPhone X","iPhone XR","iPhone XS","iPhone 11","iPhone 11 Pro","iPhone 11 Pro Max","iPhone 12","iPhone 12 Pro","iPhone 12 Pro Max","iPhone 12 Mini","iPhone 13","iPhone 13 Pro","iPhone 13 Pro Max","iPhone 14","iPhone 14 Plus","iPhone 14 Pro","iPhone 14 Pro Max"]}],"images":[{"id":36736885620960,"product_id":7487927156960,"position":1,"created_at":"2022-03-03T17:14:12+00:00","updated_at":"2022-03-03T17:14:12+00:00","alt":"Brunch Bear iPhone Case with Charm - Kawaiies - Adorable - Cute - Plushies - Plush - Kawaii","width":800,"height":800,"src":"https:\/\/cdn.shopify.com\/s\/files\/1\/0306\/9794\/7272\/products\/kawaiies-plushies-plush-softtoy-brunch-bear-iphone-case-with-charm-accessories-203654.jpg?v=1646327652","variant_ids":[]},{"id":36736882966752,"product_id":7487927156960,"position":2,"created_at":"2022-03-03T17:13:19+00:00","updated_at":"2022-03-03T17:13:19+00:00","alt":"Brunch Bear iPhone Case with Charm - Kawaiies - Adorable - Cute - Plushies - Plush - Kawaii","width":800,"height":800,"src":"https:\/\/cdn.shopify.com\/s\/files\/1\/0306\/9794\/7272\/products\/kawaiies-plushies-plush-softtoy-brunch-bear-iphone-case-with-charm-accessories-brown-iphone-12-pro-max-673194.jpg?v=1646327599","variant_ids":[42172740272352,42172740305120,42172740337888,42172740370656,42172740403424,42172740436192,42172740468960,42172740501728,42172741026016,42172741058784,42172741222624,42172741255392,42172741288160,42172741320928,42172741353696,42172741386464,42172741419232,43911485817056,43911485882592,43911485915360,43911485948128]},{"id":36736865272032,"product_id":7487927156960,"position":3,"created_at":"2022-03-03T17:06:58+00:00","updated_at":"2022-03-03T17:06:58+00:00","alt":"Brunch Bear iPhone Case with Charm - Kawaiies - Adorable - Cute - Plushies - Plush - Kawaii","width":800,"height":800,"src":"https:\/\/cdn.shopify.com\/s\/files\/1\/0306\/9794\/7272\/products\/kawaiies-plushies-plush-softtoy-brunch-bear-iphone-case-with-charm-accessories-306462.jpg?v=1646327218","variant_ids":[]},{"id":36737023607008,"product_id":7487927156960,"position":4,"created_at":"2022-03-03T17:59:09+00:00","updated_at":"2022-03-03T17:59:09+00:00","alt":"Brunch Bear iPhone Case with Charm - Kawaiies - Adorable - Cute - Plushies - Plush - Kawaii","width":800,"height":800,"src":"https:\/\/cdn.shopify.com\/s\/files\/1\/0306\/9794\/7272\/products\/kawaiies-plushies-plush-softtoy-brunch-bear-iphone-case-with-charm-accessories-beige-iphone-7-plus-198973.jpg?v=1646330349","variant_ids":[42172740534496,42172740567264,42172740600032,42172740632800,42172740665568,42172740698336,42172740731104,42172740763872,42172740829408,42172740894944,42172740927712,42172740960480,42172740993248,42172741091552,42172741124320,42172741157088,42172741189856,43911485980896,43911486013664,43911486046432,43911486079200]},{"id":36737007026400,"product_id":7487927156960,"position":5,"created_at":"2022-03-03T17:54:21+00:00","updated_at":"2022-03-03T17:54:21+00:00","alt":"Brunch Bear iPhone Case with Charm - Kawaiies - Adorable - Cute - Plushies - Plush - Kawaii","width":800,"height":800,"src":"https:\/\/cdn.shopify.com\/s\/files\/1\/0306\/9794\/7272\/products\/kawaiies-plushies-plush-softtoy-brunch-bear-iphone-case-with-charm-accessories-852578.jpg?v=1646330061","variant_ids":[]},{"id":36736867664096,"product_id":7487927156960,"position":6,"created_at":"2022-03-03T17:08:08+00:00","updated_at":"2022-03-03T17:08:08+00:00","alt":"Brunch Bear iPhone Case with Charm - Kawaiies - Adorable - Cute - Plushies - Plush - Kawaii","width":800,"height":800,"src":"https:\/\/cdn.shopify.com\/s\/files\/1\/0306\/9794\/7272\/products\/kawaiies-plushies-plush-softtoy-brunch-bear-iphone-case-with-charm-accessories-560633.jpg?v=1646327288","variant_ids":[]},{"id":36737124925664,"product_id":7487927156960,"position":7,"created_at":"2022-03-03T18:24:57+00:00","updated_at":"2022-03-03T18:24:57+00:00","alt":"Brunch Bear iPhone Case with Charm - Kawaiies - Adorable - Cute - Plushies - Plush - Kawaii","width":800,"height":800,"src":"https:\/\/cdn.shopify.com\/s\/files\/1\/0306\/9794\/7272\/products\/kawaiies-plushies-plush-softtoy-brunch-bear-iphone-case-with-charm-accessories-733790.jpg?v=1646331897","variant_ids":[]},{"id":36736960102624,"product_id":7487927156960,"position":8,"created_at":"2022-03-03T17:39:46+00:00","updated_at":"2022-03-03T17:39:46+00:00","alt":"Brunch Bear iPhone Case with Charm - Kawaiies - Adorable - Cute - Plushies - Plush - Kawaii","width":800,"height":800,"src":"https:\/\/cdn.shopify.com\/s\/files\/1\/0306\/9794\/7272\/products\/kawaiies-plushies-plush-softtoy-brunch-bear-iphone-case-with-charm-accessories-526227.jpg?v=1646329186","variant_ids":[]},{"id":36737027801312,"product_id":7487927156960,"position":9,"created_at":"2022-03-03T17:59:59+00:00","updated_at":"2022-03-03T17:59:59+00:00","alt":"Brunch Bear iPhone Case with Charm - Kawaiies - Adorable - Cute - Plushies - Plush - Kawaii","width":800,"height":800,"src":"https:\/\/cdn.shopify.com\/s\/files\/1\/0306\/9794\/7272\/products\/kawaiies-plushies-plush-softtoy-brunch-bear-iphone-case-with-charm-accessories-803040.jpg?v=1646330399","variant_ids":[]},{"id":36737067090144,"product_id":7487927156960,"position":10,"created_at":"2022-03-03T18:07:07+00:00","updated_at":"2022-03-03T18:07:07+00:00","alt":"Brunch Bear iPhone Case with Charm - Kawaiies - Adorable - Cute - Plushies - Plush - Kawaii","width":800,"height":800,"src":"https:\/\/cdn.shopify.com\/s\/files\/1\/0306\/9794\/7272\/products\/kawaiies-plushies-plush-softtoy-brunch-bear-iphone-case-with-charm-accessories-570996.jpg?v=1646330827","variant_ids":[]}],"image":{"id":36736885620960,"product_id":7487927156960,"position":1,"created_at":"2022-03-03T17:14:12+00:00","updated_at":"2022-03-03T17:14:12+00:00","alt":"Brunch Bear iPhone Case with Charm - Kawaiies - Adorable - Cute - Plushies - Plush - Kawaii","width":800,"height":800,"src":"https:\/\/cdn.shopify.com\/s\/files\/1\/0306\/9794\/7272\/products\/kawaiies-plushies-plush-softtoy-brunch-bear-iphone-case-with-charm-accessories-203654.jpg?v=1646327652","variant_ids":[]}}}