{"product":{"id":8098613657824,"title":"Poppy the Prehistoric Purussaurus Crocodile Plushie | NEW","body_html":"\u003cul class=\"tabs\"\u003e\n\u003cli\u003e\u003ca class=\"active\" href=\"#tab1\" style=\"color: #404750;\" data-mce-style=\"color: #404750;\"\u003eDescription\u003c\/a\u003e\u003c\/li\u003e\n\u003cli\u003e\u003ca href=\"#tab2\" style=\"color: #404750;\" data-mce-style=\"color: #404750;\"\u003eCleaning\u003c\/a\u003e\u003c\/li\u003e\n\u003cli\u003e\u003ca href=\"#tab3\" style=\"color: #404750;\" data-mce-style=\"color: #404750;\"\u003eShipping\u003c\/a\u003e\u003c\/li\u003e\n\u003c\/ul\u003e\n\u003cul class=\"tabs-content\"\u003e\n\u003cli class=\"active\" id=\"tab1\"\u003e\n\u003ch2\u003e\u003cspan\u003eShe's humongous and huggable!\u00a0\u003c\/span\u003e\u003c\/h2\u003e\n\u003cp\u003e\u003cspan data-mce-fragment=\"1\"\u003eAdopt a ferocious Poppy \ud83d\ude0d! \u003cbr data-mce-fragment=\"1\"\u003e\u003cbr data-mce-fragment=\"1\"\u003eThis enormous Prehistoric Purussaurus Crocodile Plushie may look intimidating, but she's nothing but friendly. All she needs is some love and she'll be showing you her poppy love to you in no time!\u003cbr\u003e\u003cbr\u003eA prehistoric pal with a modern day smile!\u00a0Poppy is a unique and adorable plushie that will make you feel like you have a piece of history in your arms. She is perfect for anyone who loves dinosaurs, crocodiles or mythology. Order yours today and get ready for some prehistoric fun!\u003cbr\u003e\u003cbr\u003ePlushie is made of high-quality materials and is safe for children of all ages. Order yours today and get ready to smile!\u003cbr\u003e\u003c\/span\u003e\u003c\/p\u003e\n\u003ch2\u003e\u003cspan\u003eThe perfect gift for your loved ones!\u003c\/span\u003e\u003c\/h2\u003e\n\u003cp\u003eWhether you throw this plush into bed with you before going to sleep or give it to someone as a present, everyone will fall in love with our gentle chicken plush. Your loved ones will enjoy the company of our chubby round chicken, so be sure to surprise them with one today!\u003cbr\u003e\u003cbr\u003e\u003c\/p\u003e\n\u003ch3\u003e\u003cspan\u003eFeatures\u003c\/span\u003e\u003c\/h3\u003e\n\u003cp\u003e\u2728 \u003cspan data-mce-fragment=\"1\"\u003eFilled with 100% premium PP cotton\u003c\/span\u003e\u003cbr\u003e \ud83d\ude34 Helps with your sleeping position\u003cbr\u003e \ud83d\udc96 Promotes relaxation with its unbelievably soft material\u003cbr\u003e \ud83d\ude0a Allergy-free and asthma friendly\u003cbr\u003e\u00a0 \u00a0 \u00a0 \u00a0 \u00a0 \u00a0 \u00a0 \u00a0 \u00a0 \u00a0 \u00a0 \u00a0 \u00a0 \u00a0 \u00a0 \u00a0 \u00a0 \u00a0 \u00a0 \u00a0 \u00a0 \u00a0 \u00a0 \u00a0 \u00a0 \u00a0 \u00a0 \u00a0 \u00a0 \u00a0 \u00a0 \u00a0 \u00a0 \u00a0 \u00a0 \u00a0 \u00a0 \u00a0 \u00a0 \u00a0 \u00a0 \u00a0 \u00a0 \u00a0 \u00a0 \u00a0 \u00a0 \u00a0 \u00a0 \u00a0 \u00a0 \u00a0 \u00a0 \u00a0 \u00a0 \u00a0 \u00a0 \u00a0 \u00a0 \u00a0 \u00a0 \u00a0 \u00a0 \u00a0 \u00a0 \u00a0 \u00a0\u003cspan data-mce-fragment=\"1\"\u003eIf you are interested in more items like this, please check out our website www.kawaiies.com.\u003c\/span\u003e\u003cspan data-mce-fragment=\"1\"\u003e\u00a0\u003c\/span\u003e \u00a0 \u00a0 \u00a0\u003c\/p\u003e\n\u003ch3\u003e\u003cspan\u003ePlushie sizes:\u003c\/span\u003e\u003c\/h3\u003e\n\u003cp\u003e\u003cspan\u003eMeasurements may be off by 1-3cm due to the nature of how PP cotton expands and compresses.\u003cbr\u003e\u003cbr\u003e\u003c\/span\u003e\u003c\/p\u003e\n\u003c\/li\u003e\n\u003cli id=\"tab2\"\u003e\n\u003cp\u003e\u003cstrong\u003eStep 1:\u003c\/strong\u003e Use the gentlest cycle available on your washing machine.\u003c\/p\u003e\n\u003cp\u003e\u003cstrong\u003eStep 2:\u003c\/strong\u003e Wash our plushie in cold water using a mild detergent.\u003c\/p\u003e\n\u003cp\u003e\u003cstrong\u003eStep 3:\u003c\/strong\u003e If disinfecting is a concern, use warm water or consider using a product like Lysol Laundry Sanitizer, which is safe on both whites and colors, unlike chlorine bleach.\u003c\/p\u003e\n\u003cp\u003e\u003cstrong\u003eStep 4:\u003c\/strong\u003e Place the plushie in a launderable mesh bag or duvet cover. Padding the drum of the washer with towels can also add another layer of protection. Recommended!\u003c\/p\u003e\n\u003cp\u003e\u003cstrong\u003eStep 5:\u003c\/strong\u003e Air-drying will be the gentlest choice, and a hairdryer turned on low heat can help to fluff up the fur once the plushie has reached the just-damp stage (think of it as a finishing touch!)\u003c\/p\u003e\n\u003c\/li\u003e\n\u003cli id=\"tab3\"\u003e\n\u003cp\u003eFREE Tracked Shipping to the United States, Canada, United Kingdom, Australia, New Zealand, Germany, Spain, France, Italy, Austria, Netherlands, and many more.\u00a0Find out more\u00a0here:\u00a0\u003ca href=\"https:\/\/www.kawaiies.com\/pages\/shipping-delivery\" target=\"_blank\"\u003eShipping Policy\u003c\/a\u003e.\u003c\/p\u003e\n\u003cbr\u003e\n\u003cp\u003e\u003cstrong\u003ePackaging time\u003c\/strong\u003e: 1-3 Business days\u003c\/p\u003e\n\u003cp\u003e\u003cstrong\u003eShipping time\u003c\/strong\u003e: 5-20 Business days\u003c\/p\u003e\n\u003c\/li\u003e\n\u003c\/ul\u003e\n\u003cp\u003e\u00a0\u003c\/p\u003e","vendor":"Soft toy","product_type":"Soft toy","created_at":"2023-09-10T16:58:03+01:00","handle":"poppy-the-prehistoric-purussaurus-crocodile-plushie","updated_at":"2024-02-11T07:55:22+00:00","published_at":"2023-09-10T17:13:48+01:00","template_suffix":null,"published_scope":"web","tags":"Alligator, Alligators, croc, Crocodile, Crocodiles, dino, dino plushie, Dinos, Dinosaur, dinosaur plushie, Dinosaurs, jurassic, prehistoric","variants":[{"id":44176892952800,"product_id":8098613657824,"title":"31in \/ 80cm \/ Pinky","price":"32.99","sku":"3256805841784246-pink-80cm","position":1,"compare_at_price":"43.00","fulfillment_service":"dsers-fulfillment-service","inventory_management":"shopify","option1":"31in \/ 80cm","option2":"Pinky","option3":null,"created_at":"2023-09-10T16:58:03+01:00","updated_at":"2024-02-11T07:55:22+00:00","taxable":false,"barcode":null,"grams":0,"image_id":39186115821792,"weight":0.0,"weight_unit":"g","requires_shipping":true},{"id":44176892985568,"product_id":8098613657824,"title":"31in \/ 80cm \/ Pansy","price":"32.99","sku":"3256805841784246-light purple-80cm","position":2,"compare_at_price":"43.00","fulfillment_service":"dsers-fulfillment-service","inventory_management":"shopify","option1":"31in \/ 80cm","option2":"Pansy","option3":null,"created_at":"2023-09-10T16:58:03+01:00","updated_at":"2024-02-11T07:55:22+00:00","taxable":false,"barcode":null,"grams":0,"image_id":39186116280544,"weight":0.0,"weight_unit":"g","requires_shipping":true},{"id":44176893018336,"product_id":8098613657824,"title":"31in \/ 80cm \/ Neon Bulb","price":"32.99","sku":"3256805841784246-light green-80cm","position":3,"compare_at_price":"43.00","fulfillment_service":"dsers-fulfillment-service","inventory_management":"shopify","option1":"31in \/ 80cm","option2":"Neon Bulb","option3":null,"created_at":"2023-09-10T16:58:03+01:00","updated_at":"2024-02-11T07:55:22+00:00","taxable":false,"barcode":null,"grams":0,"image_id":39186116247776,"weight":0.0,"weight_unit":"g","requires_shipping":true},{"id":44176893051104,"product_id":8098613657824,"title":"31in \/ 80cm \/ MudBath","price":"32.99","sku":"3256805841784246-dark purple-80cm","position":4,"compare_at_price":"43.00","fulfillment_service":"dsers-fulfillment-service","inventory_management":"shopify","option1":"31in \/ 80cm","option2":"MudBath","option3":null,"created_at":"2023-09-10T16:58:03+01:00","updated_at":"2024-02-11T07:55:22+00:00","taxable":false,"barcode":null,"grams":0,"image_id":39186115854560,"weight":0.0,"weight_unit":"g","requires_shipping":true},{"id":44176893083872,"product_id":8098613657824,"title":"31in \/ 80cm \/ Forest Gump","price":"32.99","sku":"3256805841784246-dark green-80cm","position":5,"compare_at_price":"43.00","fulfillment_service":"dsers-fulfillment-service","inventory_management":"shopify","option1":"31in \/ 80cm","option2":"Forest Gump","option3":null,"created_at":"2023-09-10T16:58:03+01:00","updated_at":"2024-02-11T07:55:22+00:00","taxable":false,"barcode":null,"grams":0,"image_id":39186116018400,"weight":0.0,"weight_unit":"g","requires_shipping":true},{"id":44176893608160,"product_id":8098613657824,"title":"39in \/ 100cm \/ Pinky","price":"44.99","sku":"3256805841784246-pink-100cm","position":6,"compare_at_price":"58.00","fulfillment_service":"dsers-fulfillment-service","inventory_management":"shopify","option1":"39in \/ 100cm","option2":"Pinky","option3":null,"created_at":"2023-09-10T16:58:03+01:00","updated_at":"2024-02-11T07:55:22+00:00","taxable":false,"barcode":null,"grams":0,"image_id":39186115821792,"weight":0.0,"weight_unit":"g","requires_shipping":true},{"id":44176893640928,"product_id":8098613657824,"title":"39in \/ 100cm \/ Pansy","price":"44.99","sku":"3256805841784246-light purple-100cm","position":7,"compare_at_price":"58.00","fulfillment_service":"dsers-fulfillment-service","inventory_management":"shopify","option1":"39in \/ 100cm","option2":"Pansy","option3":null,"created_at":"2023-09-10T16:58:03+01:00","updated_at":"2024-02-11T07:55:22+00:00","taxable":false,"barcode":null,"grams":0,"image_id":39186116280544,"weight":0.0,"weight_unit":"g","requires_shipping":true},{"id":44176893673696,"product_id":8098613657824,"title":"39in \/ 100cm \/ Neon Bulb","price":"44.99","sku":"3256805841784246-light green-100cm","position":8,"compare_at_price":"58.00","fulfillment_service":"dsers-fulfillment-service","inventory_management":"shopify","option1":"39in \/ 100cm","option2":"Neon Bulb","option3":null,"created_at":"2023-09-10T16:58:03+01:00","updated_at":"2024-02-11T07:55:22+00:00","taxable":false,"barcode":null,"grams":0,"image_id":39186116247776,"weight":0.0,"weight_unit":"g","requires_shipping":true},{"id":44176893706464,"product_id":8098613657824,"title":"39in \/ 100cm \/ MudBath","price":"44.99","sku":"3256805841784246-dark purple-100cm","position":9,"compare_at_price":"58.00","fulfillment_service":"dsers-fulfillment-service","inventory_management":"shopify","option1":"39in \/ 100cm","option2":"MudBath","option3":null,"created_at":"2023-09-10T16:58:03+01:00","updated_at":"2024-02-11T07:55:22+00:00","taxable":false,"barcode":null,"grams":0,"image_id":39186115854560,"weight":0.0,"weight_unit":"g","requires_shipping":true},{"id":44176893739232,"product_id":8098613657824,"title":"39in \/ 100cm \/ Forest Gump","price":"44.99","sku":"3256805841784246-dark green-100cm","position":10,"compare_at_price":"58.00","fulfillment_service":"dsers-fulfillment-service","inventory_management":"shopify","option1":"39in \/ 100cm","option2":"Forest Gump","option3":null,"created_at":"2023-09-10T16:58:03+01:00","updated_at":"2024-02-11T07:55:22+00:00","taxable":false,"barcode":null,"grams":0,"image_id":39186116018400,"weight":0.0,"weight_unit":"g","requires_shipping":true},{"id":44176893444320,"product_id":8098613657824,"title":"47in \/ 120cm \/ Pinky","price":"61.99","sku":"3256805841784246-pink-120cm","position":11,"compare_at_price":"80.00","fulfillment_service":"dsers-fulfillment-service","inventory_management":"shopify","option1":"47in \/ 120cm","option2":"Pinky","option3":null,"created_at":"2023-09-10T16:58:03+01:00","updated_at":"2024-02-11T07:55:22+00:00","taxable":false,"barcode":null,"grams":0,"image_id":39186115821792,"weight":0.0,"weight_unit":"g","requires_shipping":true},{"id":44176893477088,"product_id":8098613657824,"title":"47in \/ 120cm \/ Pansy","price":"61.99","sku":"3256805841784246-light purple-120cm","position":12,"compare_at_price":"80.00","fulfillment_service":"dsers-fulfillment-service","inventory_management":"shopify","option1":"47in \/ 120cm","option2":"Pansy","option3":null,"created_at":"2023-09-10T16:58:03+01:00","updated_at":"2024-02-11T07:55:22+00:00","taxable":false,"barcode":null,"grams":0,"image_id":39186116280544,"weight":0.0,"weight_unit":"g","requires_shipping":true},{"id":44176893509856,"product_id":8098613657824,"title":"47in \/ 120cm \/ Neon Bulb","price":"61.99","sku":"3256805841784246-light green-120cm","position":13,"compare_at_price":"80.00","fulfillment_service":"dsers-fulfillment-service","inventory_management":"shopify","option1":"47in \/ 120cm","option2":"Neon Bulb","option3":null,"created_at":"2023-09-10T16:58:03+01:00","updated_at":"2024-02-11T07:55:22+00:00","taxable":false,"barcode":null,"grams":0,"image_id":39186116247776,"weight":0.0,"weight_unit":"g","requires_shipping":true},{"id":44176893542624,"product_id":8098613657824,"title":"47in \/ 120cm \/ MudBath","price":"61.99","sku":"3256805841784246-dark purple-120cm","position":14,"compare_at_price":"80.00","fulfillment_service":"dsers-fulfillment-service","inventory_management":"shopify","option1":"47in \/ 120cm","option2":"MudBath","option3":null,"created_at":"2023-09-10T16:58:03+01:00","updated_at":"2024-02-11T07:55:22+00:00","taxable":false,"barcode":null,"grams":0,"image_id":39186115854560,"weight":0.0,"weight_unit":"g","requires_shipping":true},{"id":44176893575392,"product_id":8098613657824,"title":"47in \/ 120cm \/ Forest Gump","price":"61.99","sku":"3256805841784246-dark green-120cm","position":15,"compare_at_price":"80.00","fulfillment_service":"dsers-fulfillment-service","inventory_management":"shopify","option1":"47in \/ 120cm","option2":"Forest Gump","option3":null,"created_at":"2023-09-10T16:58:03+01:00","updated_at":"2024-02-11T07:55:22+00:00","taxable":false,"barcode":null,"grams":0,"image_id":39186116018400,"weight":0.0,"weight_unit":"g","requires_shipping":true},{"id":44176893280480,"product_id":8098613657824,"title":"55in \/ 140cm \/ Pinky","price":"94.99","sku":"3256805841784246-pink-140cm","position":16,"compare_at_price":"120.00","fulfillment_service":"dsers-fulfillment-service","inventory_management":"shopify","option1":"55in \/ 140cm","option2":"Pinky","option3":null,"created_at":"2023-09-10T16:58:03+01:00","updated_at":"2024-02-11T07:55:22+00:00","taxable":false,"barcode":null,"grams":0,"image_id":39186115821792,"weight":0.0,"weight_unit":"g","requires_shipping":true},{"id":44176893313248,"product_id":8098613657824,"title":"55in \/ 140cm \/ Pansy","price":"94.99","sku":"3256805841784246-light purple-140cm","position":17,"compare_at_price":"120.00","fulfillment_service":"dsers-fulfillment-service","inventory_management":"shopify","option1":"55in \/ 140cm","option2":"Pansy","option3":null,"created_at":"2023-09-10T16:58:03+01:00","updated_at":"2024-02-11T07:55:22+00:00","taxable":false,"barcode":null,"grams":0,"image_id":39186116280544,"weight":0.0,"weight_unit":"g","requires_shipping":true},{"id":44176893346016,"product_id":8098613657824,"title":"55in \/ 140cm \/ Neon Bulb","price":"94.99","sku":"3256805841784246-light green-140cm","position":18,"compare_at_price":"120.00","fulfillment_service":"dsers-fulfillment-service","inventory_management":"shopify","option1":"55in \/ 140cm","option2":"Neon Bulb","option3":null,"created_at":"2023-09-10T16:58:03+01:00","updated_at":"2024-02-11T07:55:22+00:00","taxable":false,"barcode":null,"grams":0,"image_id":39186116247776,"weight":0.0,"weight_unit":"g","requires_shipping":true},{"id":44176893378784,"product_id":8098613657824,"title":"55in \/ 140cm \/ MudBath","price":"94.99","sku":"3256805841784246-dark purple-140cm","position":19,"compare_at_price":"120.00","fulfillment_service":"dsers-fulfillment-service","inventory_management":"shopify","option1":"55in \/ 140cm","option2":"MudBath","option3":null,"created_at":"2023-09-10T16:58:03+01:00","updated_at":"2024-02-11T07:55:22+00:00","taxable":false,"barcode":null,"grams":0,"image_id":39186115854560,"weight":0.0,"weight_unit":"g","requires_shipping":true},{"id":44176893411552,"product_id":8098613657824,"title":"55in \/ 140cm \/ Forest Gump","price":"94.99","sku":"3256805841784246-dark green-140cm","position":20,"compare_at_price":"120.00","fulfillment_service":"dsers-fulfillment-service","inventory_management":"shopify","option1":"55in \/ 140cm","option2":"Forest Gump","option3":null,"created_at":"2023-09-10T16:58:03+01:00","updated_at":"2024-02-11T07:55:22+00:00","taxable":false,"barcode":null,"grams":0,"image_id":39186116018400,"weight":0.0,"weight_unit":"g","requires_shipping":true},{"id":44176893116640,"product_id":8098613657824,"title":"62in \/ 160cm \/ Pinky","price":"204.99","sku":"3256805841784246-pink-160cm","position":21,"compare_at_price":"270.00","fulfillment_service":"dsers-fulfillment-service","inventory_management":"shopify","option1":"62in \/ 160cm","option2":"Pinky","option3":null,"created_at":"2023-09-10T16:58:03+01:00","updated_at":"2024-02-11T07:55:22+00:00","taxable":false,"barcode":null,"grams":0,"image_id":39186115821792,"weight":0.0,"weight_unit":"g","requires_shipping":true},{"id":44176893149408,"product_id":8098613657824,"title":"62in \/ 160cm \/ Pansy","price":"204.99","sku":"3256805841784246-light purple-160cm","position":22,"compare_at_price":"270.00","fulfillment_service":"dsers-fulfillment-service","inventory_management":"shopify","option1":"62in \/ 160cm","option2":"Pansy","option3":null,"created_at":"2023-09-10T16:58:03+01:00","updated_at":"2024-02-11T07:55:22+00:00","taxable":false,"barcode":null,"grams":0,"image_id":39186116280544,"weight":0.0,"weight_unit":"g","requires_shipping":true},{"id":44176893182176,"product_id":8098613657824,"title":"62in \/ 160cm \/ Neon Bulb","price":"204.99","sku":"3256805841784246-light green-160cm","position":23,"compare_at_price":"270.00","fulfillment_service":"dsers-fulfillment-service","inventory_management":"shopify","option1":"62in \/ 160cm","option2":"Neon Bulb","option3":null,"created_at":"2023-09-10T16:58:03+01:00","updated_at":"2024-02-11T07:55:22+00:00","taxable":false,"barcode":null,"grams":0,"image_id":39186116247776,"weight":0.0,"weight_unit":"g","requires_shipping":true},{"id":44176893214944,"product_id":8098613657824,"title":"62in \/ 160cm \/ MudBath","price":"204.99","sku":"3256805841784246-dark purple-160cm","position":24,"compare_at_price":"270.00","fulfillment_service":"dsers-fulfillment-service","inventory_management":"shopify","option1":"62in \/ 160cm","option2":"MudBath","option3":null,"created_at":"2023-09-10T16:58:03+01:00","updated_at":"2024-02-11T07:55:22+00:00","taxable":false,"barcode":null,"grams":0,"image_id":39186115854560,"weight":0.0,"weight_unit":"g","requires_shipping":true},{"id":44176893247712,"product_id":8098613657824,"title":"62in \/ 160cm \/ Forest Gump","price":"204.99","sku":"3256805841784246-dark green-160cm","position":25,"compare_at_price":"270.00","fulfillment_service":"dsers-fulfillment-service","inventory_management":"shopify","option1":"62in \/ 160cm","option2":"Forest Gump","option3":null,"created_at":"2023-09-10T16:58:03+01:00","updated_at":"2024-02-11T07:55:22+00:00","taxable":false,"barcode":null,"grams":0,"image_id":39186116018400,"weight":0.0,"weight_unit":"g","requires_shipping":true}],"options":[{"id":10329493668064,"product_id":8098613657824,"name":"Length","position":1,"values":["31in \/ 80cm","39in \/ 100cm","47in \/ 120cm","55in \/ 140cm","62in \/ 160cm"]},{"id":10329493635296,"product_id":8098613657824,"name":"Names","position":2,"values":["Pinky","Pansy","Neon Bulb","MudBath","Forest Gump"]}],"images":[{"id":39186119753952,"product_id":8098613657824,"position":1,"created_at":"2023-09-10T17:11:39+01:00","updated_at":"2023-09-12T15:07:17+01:00","alt":"Poppy the Prehistoric Purussaurus Crocodile Plushie | NEW - Kawaiies - Adorable - Cute - Plushies - Plush - Kawaii","width":800,"height":800,"src":"https:\/\/cdn.shopify.com\/s\/files\/1\/0306\/9794\/7272\/files\/kawaiies-plushies-plush-softtoy-francis-the-fossil-dino-buddy-soft-toy-573819_05eabe7d-45d4-4225-a929-0919618ca1b9.jpg?v=1694527637","variant_ids":[]},{"id":39186115723488,"product_id":8098613657824,"position":2,"created_at":"2023-09-10T16:58:03+01:00","updated_at":"2023-09-12T15:07:17+01:00","alt":"Poppy the Prehistoric Purussaurus Crocodile Plushie | NEW - Kawaiies - Adorable - Cute - Plushies - Plush - Kawaii","width":1000,"height":1000,"src":"https:\/\/cdn.shopify.com\/s\/files\/1\/0306\/9794\/7272\/products\/S37105295e9cf4b8b89e2c363ebf1483d6.jpg?v=1694527637","variant_ids":[]},{"id":39186119622880,"product_id":8098613657824,"position":3,"created_at":"2023-09-10T17:11:39+01:00","updated_at":"2023-09-12T15:07:17+01:00","alt":"Poppy the Prehistoric Purussaurus Crocodile Plushie | NEW - Kawaiies - Adorable - Cute - Plushies - Plush - Kawaii","width":800,"height":800,"src":"https:\/\/cdn.shopify.com\/s\/files\/1\/0306\/9794\/7272\/files\/wwwkawaiiescom0909c_2_92eb6078-89fa-457b-94cb-e3c445a340e0.jpg?v=1694527637","variant_ids":[]},{"id":39186115821792,"product_id":8098613657824,"position":4,"created_at":"2023-09-10T16:58:10+01:00","updated_at":"2023-09-12T15:07:17+01:00","alt":"Poppy the Prehistoric Purussaurus Crocodile Plushie | NEW - Kawaiies - Adorable - Cute - Plushies - Plush - Kawaii","width":1000,"height":1000,"src":"https:\/\/cdn.shopify.com\/s\/files\/1\/0306\/9794\/7272\/files\/Sc067445b80374689a992d3b520c5931dr.jpg?v=1694527637","variant_ids":[44176892952800,44176893116640,44176893280480,44176893444320,44176893608160]},{"id":39186115854560,"product_id":8098613657824,"position":5,"created_at":"2023-09-10T16:58:14+01:00","updated_at":"2023-09-12T15:07:17+01:00","alt":"Poppy the Prehistoric Purussaurus Crocodile Plushie | NEW - Kawaiies - Adorable - Cute - Plushies - Plush - Kawaii","width":1000,"height":1000,"src":"https:\/\/cdn.shopify.com\/s\/files\/1\/0306\/9794\/7272\/files\/S65be4450b1e3407eb2c9e44b4243356aq.jpg?v=1694527637","variant_ids":[44176893051104,44176893214944,44176893378784,44176893542624,44176893706464]},{"id":39186116018400,"product_id":8098613657824,"position":6,"created_at":"2023-09-10T16:58:18+01:00","updated_at":"2023-09-12T15:07:17+01:00","alt":"Poppy the Prehistoric Purussaurus Crocodile Plushie | NEW - Kawaiies - Adorable - Cute - Plushies - Plush - Kawaii","width":1000,"height":1000,"src":"https:\/\/cdn.shopify.com\/s\/files\/1\/0306\/9794\/7272\/files\/Se3e41a2ec1b943e49e47eccce055be81s.jpg?v=1694527637","variant_ids":[44176893083872,44176893247712,44176893411552,44176893575392,44176893739232]},{"id":39186116247776,"product_id":8098613657824,"position":7,"created_at":"2023-09-10T16:58:22+01:00","updated_at":"2023-09-12T15:07:17+01:00","alt":"Poppy the Prehistoric Purussaurus Crocodile Plushie | NEW - Kawaiies - Adorable - Cute - Plushies - Plush - Kawaii","width":1000,"height":1000,"src":"https:\/\/cdn.shopify.com\/s\/files\/1\/0306\/9794\/7272\/files\/Sc27159b13af8480c8f7845781c81ec34I.jpg?v=1694527637","variant_ids":[44176893018336,44176893182176,44176893346016,44176893509856,44176893673696]},{"id":39186116280544,"product_id":8098613657824,"position":8,"created_at":"2023-09-10T16:58:24+01:00","updated_at":"2023-09-12T15:07:17+01:00","alt":"Poppy the Prehistoric Purussaurus Crocodile Plushie | NEW - Kawaiies - Adorable - Cute - Plushies - Plush - Kawaii","width":1000,"height":1000,"src":"https:\/\/cdn.shopify.com\/s\/files\/1\/0306\/9794\/7272\/files\/S1bae8f316d0d429a9926af19715112d5L.jpg?v=1694527637","variant_ids":[44176892985568,44176893149408,44176893313248,44176893477088,44176893640928]},{"id":39186119721184,"product_id":8098613657824,"position":9,"created_at":"2023-09-10T17:11:39+01:00","updated_at":"2023-09-12T15:07:17+01:00","alt":"Poppy the Prehistoric Purussaurus Crocodile Plushie | NEW - Kawaiies - Adorable - Cute - Plushies - Plush - Kawaii","width":800,"height":800,"src":"https:\/\/cdn.shopify.com\/s\/files\/1\/0306\/9794\/7272\/files\/wwwkawaiiescom0909c_12_dc93ffdd-9b6c-4aea-a6bd-2f8355ff5c6f.jpg?v=1694527637","variant_ids":[]},{"id":39186119885024,"product_id":8098613657824,"position":10,"created_at":"2023-09-10T17:11:39+01:00","updated_at":"2023-09-12T15:07:17+01:00","alt":"Poppy the Prehistoric Purussaurus Crocodile Plushie | NEW - Kawaiies - Adorable - Cute - Plushies - Plush - Kawaii","width":800,"height":800,"src":"https:\/\/cdn.shopify.com\/s\/files\/1\/0306\/9794\/7272\/files\/wwwkawaiiescom0909c_6_b875b97e-329b-4d4b-81f6-71ed1319c236.jpg?v=1694527637","variant_ids":[]},{"id":39186119655648,"product_id":8098613657824,"position":11,"created_at":"2023-09-10T17:11:39+01:00","updated_at":"2023-09-12T15:07:17+01:00","alt":"Poppy the Prehistoric Purussaurus Crocodile Plushie | NEW - Kawaiies - Adorable - Cute - Plushies - Plush - Kawaii","width":800,"height":800,"src":"https:\/\/cdn.shopify.com\/s\/files\/1\/0306\/9794\/7272\/files\/wwwkawaiiescom0909c_7_5dd5de90-7865-4caa-a430-2d82d2bcc509.jpg?v=1694527637","variant_ids":[]},{"id":39186119688416,"product_id":8098613657824,"position":12,"created_at":"2023-09-10T17:11:39+01:00","updated_at":"2023-09-12T15:07:17+01:00","alt":"Poppy the Prehistoric Purussaurus Crocodile Plushie | NEW - Kawaiies - Adorable - Cute - Plushies - Plush - Kawaii","width":671,"height":671,"src":"https:\/\/cdn.shopify.com\/s\/files\/1\/0306\/9794\/7272\/files\/H4d71510ba43248ee8ec0564c8bc0a9d44_3a201878-b851-4214-ba6a-b42278c9fa4b.jpg?v=1694527637","variant_ids":[]},{"id":39186119917792,"product_id":8098613657824,"position":13,"created_at":"2023-09-10T17:11:39+01:00","updated_at":"2023-09-12T15:07:17+01:00","alt":"Poppy the Prehistoric Purussaurus Crocodile Plushie | NEW - Kawaiies - Adorable - Cute - Plushies - Plush - Kawaii","width":790,"height":790,"src":"https:\/\/cdn.shopify.com\/s\/files\/1\/0306\/9794\/7272\/files\/wwwkawaiiescom0909d_2_-Copy_2201f91d-ee0f-4a39-997a-3b2225d63c20.jpg?v=1694527637","variant_ids":[]},{"id":39186119983328,"product_id":8098613657824,"position":14,"created_at":"2023-09-10T17:11:39+01:00","updated_at":"2023-09-12T15:07:17+01:00","alt":"Poppy the Prehistoric Purussaurus Crocodile Plushie | NEW - Kawaiies - Adorable - Cute - Plushies - Plush - Kawaii","width":800,"height":800,"src":"https:\/\/cdn.shopify.com\/s\/files\/1\/0306\/9794\/7272\/files\/kawaiies-plushies-plush-softtoy-francis-the-fossil-dino-buddy-soft-toy-332425_cc1cdc8b-7e8f-47f1-a214-5cff2a1278cf.jpg?v=1694527637","variant_ids":[]},{"id":39186119524576,"product_id":8098613657824,"position":15,"created_at":"2023-09-10T17:11:39+01:00","updated_at":"2023-09-12T15:07:17+01:00","alt":"Poppy the Prehistoric Purussaurus Crocodile Plushie | NEW - Kawaiies - Adorable - Cute - Plushies - Plush - Kawaii","width":790,"height":790,"src":"https:\/\/cdn.shopify.com\/s\/files\/1\/0306\/9794\/7272\/files\/H18987c29dd4c4c20a96094db6db54fbfe_1.jpg?v=1694527637","variant_ids":[]},{"id":39186119852256,"product_id":8098613657824,"position":16,"created_at":"2023-09-10T17:11:39+01:00","updated_at":"2023-09-12T15:07:17+01:00","alt":"Poppy the Prehistoric Purussaurus Crocodile Plushie | NEW - Kawaiies - Adorable - Cute - Plushies - Plush - Kawaii","width":853,"height":854,"src":"https:\/\/cdn.shopify.com\/s\/files\/1\/0306\/9794\/7272\/files\/wwwkawaiiescom_3_sds_daa39d7a-0566-40d7-857b-cd82d01747e2.png?v=1694527637","variant_ids":[]},{"id":39186120081632,"product_id":8098613657824,"position":17,"created_at":"2023-09-10T17:11:46+01:00","updated_at":"2023-09-12T15:07:17+01:00","alt":"Poppy the Prehistoric Purussaurus Crocodile Plushie | NEW - Kawaiies - Adorable - Cute - Plushies - Plush - Kawaii","width":1000,"height":1000,"src":"https:\/\/cdn.shopify.com\/s\/files\/1\/0306\/9794\/7272\/files\/wwwkawaiiescom_3_ff18cf2a-a7a7-4e47-b9b6-b7ef7a41752e.jpg?v=1694527637","variant_ids":[]},{"id":39186120048864,"product_id":8098613657824,"position":18,"created_at":"2023-09-10T17:11:39+01:00","updated_at":"2023-09-12T15:07:17+01:00","alt":"Poppy the Prehistoric Purussaurus Crocodile Plushie | NEW - Kawaiies - Adorable - Cute - Plushies - Plush - Kawaii","width":869,"height":869,"src":"https:\/\/cdn.shopify.com\/s\/files\/1\/0306\/9794\/7272\/files\/wwwkawaiiescom0909d_5_d5bb18c9-7222-45f9-92c9-f8e0c7bfb20c.jpg?v=1694527637","variant_ids":[]}],"image":{"id":39186119753952,"product_id":8098613657824,"position":1,"created_at":"2023-09-10T17:11:39+01:00","updated_at":"2023-09-12T15:07:17+01:00","alt":"Poppy the Prehistoric Purussaurus Crocodile Plushie | NEW - Kawaiies - Adorable - Cute - Plushies - Plush - Kawaii","width":800,"height":800,"src":"https:\/\/cdn.shopify.com\/s\/files\/1\/0306\/9794\/7272\/files\/kawaiies-plushies-plush-softtoy-francis-the-fossil-dino-buddy-soft-toy-573819_05eabe7d-45d4-4225-a929-0919618ca1b9.jpg?v=1694527637","variant_ids":[]}}}