{"product":{"id":8098002796768,"title":"Soft Pig Fluffy Pyjama 1-Piece Set | NEW","body_html":"\u003cul class=\"tabs\"\u003e\n\u003cli\u003e\u003ca class=\"active\" href=\"#tab1\" style=\"color: #404750;\" data-mce-style=\"color: #404750;\"\u003eDescription\u003c\/a\u003e\u003c\/li\u003e\n\u003cli\u003e\u003ca href=\"#tab2\" style=\"color: #404750;\" data-mce-style=\"color: #404750;\"\u003eFAQ\u003c\/a\u003e\u003c\/li\u003e\n\u003cli\u003e\u003ca href=\"#tab3\" style=\"color: #404750;\" data-mce-style=\"color: #404750;\"\u003eShipping\u003c\/a\u003e\u003c\/li\u003e\n\u003c\/ul\u003e\n\u003cul class=\"tabs-content\"\u003e\n\u003cli class=\"active\" id=\"tab1\"\u003e\n\u003ch2\u003e\n\u003cmeta charset=\"utf-8\"\u003e \u003cspan data-mce-fragment=\"1\"\u003eSink into cosy dreams\u00a0with our Soft\u00a0Pig Fluffy Pajama 1-Piece Set\u003c\/span\u003e!\u003c\/h2\u003e\n\u003cp\u003eIntroducing a delightful blend of comfort and charm for your bedtime routine. Crafted from ultra-soft, plush materials, these pyjamas keep you cosy and content throughout the night. These pyjamas\u00a0feature an adorable piggy-style hood and\u00a0pig pockets. With an easy-opening zip and ribbed cuffs, these pyjamas offer a snug yet flexible fit for ultimate comfort.\u003cbr\u003e\u003cbr\u003eWhether you're lounging or dreaming, our\u00a0Soft\u00a0Pig Pyjama\u00a0promises to make bedtime a comfy and whimsical affair. Dive into dreamland with style and snuggles!\u003cbr\u003e\u003cbr\u003e\u003c\/p\u003e\n\u003cp\u003e\u003cspan data-mce-fragment=\"1\"\u003e\ud83c\udf38\u00a0International size: Medium\u00a0to X-Large\u003cbr\u003e\ud83c\udf38\u00a0Long sleeves \u0026amp;\u00a0hands\/legs has an elastic band\u003cbr data-mce-fragment=\"1\"\u003e\ud83c\udf38\u00a0100% premium\u00a0fleece sherpa \u0026amp; cotton\u003cbr data-mce-fragment=\"1\"\u003e\ud83c\udf38\u00a0Promotes warmth, comfort, and\u00a0durability\u003cbr data-mce-fragment=\"1\"\u003e\ud83c\udf38\u00a0Machine washable\u003cbr\u003e\u003cbr\u003e\u003c\/span\u003ePLEASE NOTE: Pyjamas are sold separately. If you want to match, please choose sizes accordingly and add to cart.\u003cimg style=\"float: none;\" alt=\"\" src=\"https:\/\/cdn.shopify.com\/s\/files\/1\/0306\/9794\/7272\/products\/l_1024x1024.jpg?v=1625504987\" data-mce-style=\"float: none;\"\u003e\u003c\/p\u003e\n\u003cdiv style=\"text-align: left;\" data-mce-style=\"text-align: left;\"\u003e\n\u003cbr\u003ePyjama Sets are\u00a0available in different sizes for all to wear, measurements are shown below. \u003cspan data-mce-fragment=\"1\"\u003eIt is best to measure your chest and length, and then choose a size according to the result to simplify the various international measurements. And if in doubt, just go one size up because oversized pyjamas are always comfy to wear!\u003cbr\u003e\u003c\/span\u003e\n\u003c\/div\u003e\n\u003cp\u003e\u003cspan\u003e\u003cbr\u003eAll sizes:\u003cbr\u003e\u003cbr\u003e\u003cmeta charset=\"utf-8\"\u003e \u003cimg src=\"https:\/\/ae01.alicdn.com\/kf\/S56deca1bc4d54543acaafdaf29ec41faA.png\" data-mce-src=\"https:\/\/ae01.alicdn.com\/kf\/S56deca1bc4d54543acaafdaf29ec41faA.png\" data-mce-fragment=\"1\"\u003e\u003cbr\u003e\u003c\/span\u003e\u003c\/p\u003e\n\u003cp\u003e\u003cspan\u003eMeasurements may be off by 1-5cm for rounding up to a whole number.\u003c\/span\u003e\u003c\/p\u003e\n\u003c\/li\u003e\n\u003cli id=\"tab2\"\u003e\n\u003cp\u003e\u003cstrong\u003ePlease follow the washing\u00a0l\u003c\/strong\u003e\u003cstrong\u003eabels when cleaning the garment:\u003c\/strong\u003e\u003c\/p\u003e\n\u003cp\u003e\u003cstrong\u003e\u003cimg alt=\"\" src=\"https:\/\/cdn.shopify.com\/s\/files\/1\/0306\/9794\/7272\/files\/30a_32x32.png?v=1616878970\" data-mce-fragment=\"1\"\u003e\u00a0\u003c\/strong\u003e\u003cspan\u003eMax temperature 30c, or cold water. Reverse garment when washing.\u003c\/span\u003e\u003c\/p\u003e\n\u003cp\u003e\u003cspan\u003e\u003c\/span\u003e\u003cstrong\u003e\u003cimg src=\"https:\/\/cdn.shopify.com\/s\/files\/1\/0306\/9794\/7272\/files\/no_bleach_32x32.png?v=1616877694\" alt=\"\" data-mce-fragment=\"1\"\u003e\u00a0\u003c\/strong\u003eDo not bleach\u003c\/p\u003e\n\u003cp\u003e\u003cstrong\u003e\u003cimg src=\"https:\/\/cdn.shopify.com\/s\/files\/1\/0306\/9794\/7272\/files\/dry_hang_32x32.png?v=1616879053\" alt=\"\" data-mce-fragment=\"1\"\u003e\u00a0\u003c\/strong\u003e\u003cspan\u003eDry by the sun or hang it to dry.\u00a0\u003c\/span\u003e\u003c\/p\u003e\n\u003cp\u003e\u003cspan\u003e\u003cstrong\u003e\u003cimg alt=\"\" src=\"https:\/\/cdn.shopify.com\/s\/files\/1\/0306\/9794\/7272\/files\/dry_C_32x32.png?v=1616879100\" data-mce-fragment=\"1\"\u003e\u00a0\u003c\/strong\u003eDry cleaning\u003c\/span\u003e\u003c\/p\u003e\n\u003cp\u003e\u00a0\u003c\/p\u003e\n\u003c\/li\u003e\n\u003cli id=\"tab3\"\u003e\n\u003cp\u003eFree Tracked Shipping to the United States, United Kingdom, Australia, New Zealand, Germany, Spain, France, Netherlands, and many more.\u003cbr\u003e\u003cbr\u003eSmall shipping fee to Canada, Italy, Switzerland, Norway, Sweden, Denmark, Ireland, Finland, United Arab Emirates and a few other countries.\u003cbr\u003e\u003cbr\u003e\u003cstrong\u003ePackaging time\u003c\/strong\u003e: Est. 1-4 Business days\u003cbr\u003e\u003cstrong\u003eShipping time\u003c\/strong\u003e: Est. 5-15 Business days\u003cbr\u003e\u003cbr\u003eFor more details and the latest shipping updates please click here:\u00a0\u003ca data-mce-fragment=\"1\" href=\"https:\/\/www.kawaiies.com\/pages\/shipping-delivery\" data-mce-href=\"https:\/\/www.kawaiies.com\/pages\/shipping-delivery\" target=\"_blank\"\u003eShipping Policy\u003c\/a\u003e.\u003c\/p\u003e\n\u003c\/li\u003e\n\u003c\/ul\u003e","vendor":"Apparel","product_type":"Apparel","created_at":"2023-09-08T21:15:29+01:00","handle":"soft-pig-fluffy-pyjama-1-piece-set","updated_at":"2024-02-11T07:55:18+00:00","published_at":"2023-09-08T23:04:46+01:00","template_suffix":null,"published_scope":"web","tags":"Apparel, Apparels, Night, Nightwear, Onesie, Pajama, Pajamas, Pig, piggy, Pigs, Pink, Pyjama, Pyjamas, Sleep, sleeping, Sleepy","variants":[{"id":44175170961632,"product_id":8098002796768,"title":"M","price":"82.99","sku":"1005005058652049-697-M","position":1,"compare_at_price":"105.00","fulfillment_service":"dsers-fulfillment-service","inventory_management":"shopify","option1":"M","option2":null,"option3":null,"created_at":"2023-09-08T21:15:29+01:00","updated_at":"2024-02-11T07:55:18+00:00","taxable":false,"barcode":null,"grams":0,"image_id":39184102719712,"weight":0.0,"weight_unit":"g","requires_shipping":true},{"id":44175170994400,"product_id":8098002796768,"title":"L","price":"82.99","sku":"1005005058652049-697-L","position":2,"compare_at_price":"105.00","fulfillment_service":"dsers-fulfillment-service","inventory_management":"shopify","option1":"L","option2":null,"option3":null,"created_at":"2023-09-08T21:15:29+01:00","updated_at":"2024-02-11T07:55:18+00:00","taxable":false,"barcode":null,"grams":0,"image_id":39184102719712,"weight":0.0,"weight_unit":"g","requires_shipping":true},{"id":44175171027168,"product_id":8098002796768,"title":"XL","price":"82.99","sku":"1005005058652049-697-XL","position":3,"compare_at_price":"105.00","fulfillment_service":"dsers-fulfillment-service","inventory_management":"shopify","option1":"XL","option2":null,"option3":null,"created_at":"2023-09-08T21:15:29+01:00","updated_at":"2024-02-11T07:55:18+00:00","taxable":false,"barcode":null,"grams":0,"image_id":39184102719712,"weight":0.0,"weight_unit":"g","requires_shipping":true}],"options":[{"id":10328608407776,"product_id":8098002796768,"name":"Size","position":1,"values":["M","L","XL"]}],"images":[{"id":39184102719712,"product_id":8098002796768,"position":1,"created_at":"2023-09-08T21:15:29+01:00","updated_at":"2023-09-08T21:15:31+01:00","alt":"Soft Pig Fluffy Pyjama 1-Piece Set | NEW - Kawaiies - Adorable - Cute - Plushies - Plush - Kawaii","width":800,"height":800,"src":"https:\/\/cdn.shopify.com\/s\/files\/1\/0306\/9794\/7272\/products\/S5f63fd6b60d74f10a7155edc33fe72bc1.jpg?v=1694204131","variant_ids":[44175170961632,44175170994400,44175171027168]},{"id":39184102949088,"product_id":8098002796768,"position":2,"created_at":"2023-09-08T21:15:34+01:00","updated_at":"2023-09-08T21:15:34+01:00","alt":"Soft Pig Fluffy Pyjama 1-Piece Set | NEW - Kawaiies - Adorable - Cute - Plushies - Plush - Kawaii","width":800,"height":800,"src":"https:\/\/cdn.shopify.com\/s\/files\/1\/0306\/9794\/7272\/files\/S3649f9632fc34bf08b1f84a73aa2d2d9w.jpg?v=1694204134","variant_ids":[]},{"id":39184102981856,"product_id":8098002796768,"position":3,"created_at":"2023-09-08T21:15:40+01:00","updated_at":"2023-09-08T21:15:40+01:00","alt":"Soft Pig Fluffy Pyjama 1-Piece Set | NEW - Kawaiies - Adorable - Cute - Plushies - Plush - Kawaii","width":800,"height":800,"src":"https:\/\/cdn.shopify.com\/s\/files\/1\/0306\/9794\/7272\/files\/S411fe5a8ba7e4bb3b66fecd2b72d0a30e.jpg?v=1694204140","variant_ids":[]},{"id":39184103014624,"product_id":8098002796768,"position":4,"created_at":"2023-09-08T21:15:43+01:00","updated_at":"2023-09-08T23:00:59+01:00","alt":"Soft Pig Fluffy Pyjama 1-Piece Set | NEW - Kawaiies - Adorable - Cute - Plushies - Plush - Kawaii","width":597,"height":597,"src":"https:\/\/cdn.shopify.com\/s\/files\/1\/0306\/9794\/7272\/files\/Sfdf6c3c06104471aace9483bc78869dak.jpg?v=1694210459","variant_ids":[]},{"id":39184103047392,"product_id":8098002796768,"position":5,"created_at":"2023-09-08T21:15:46+01:00","updated_at":"2023-09-08T23:01:15+01:00","alt":"Soft Pig Fluffy Pyjama 1-Piece Set | NEW - Kawaiies - Adorable - Cute - Plushies - Plush - Kawaii","width":614,"height":614,"src":"https:\/\/cdn.shopify.com\/s\/files\/1\/0306\/9794\/7272\/files\/S3abaa7f56448410b80fb0375ad9643f0u.jpg?v=1694210475","variant_ids":[]},{"id":39184103145696,"product_id":8098002796768,"position":6,"created_at":"2023-09-08T21:15:52+01:00","updated_at":"2023-09-08T23:02:26+01:00","alt":"Soft Pig Fluffy Pyjama 1-Piece Set | NEW - Kawaiies - Adorable - Cute - Plushies - Plush - Kawaii","width":612,"height":612,"src":"https:\/\/cdn.shopify.com\/s\/files\/1\/0306\/9794\/7272\/files\/S58642014df104797a5177ead995deed6D.jpg?v=1694210546","variant_ids":[]},{"id":39184103178464,"product_id":8098002796768,"position":7,"created_at":"2023-09-08T21:15:54+01:00","updated_at":"2023-09-08T23:02:26+01:00","alt":"Soft Pig Fluffy Pyjama 1-Piece Set | NEW - Kawaiies - Adorable - Cute - Plushies - Plush - Kawaii","width":594,"height":594,"src":"https:\/\/cdn.shopify.com\/s\/files\/1\/0306\/9794\/7272\/files\/S1c37379b2a424f29a727db957a310c4dK.jpg?v=1694210546","variant_ids":[]},{"id":39184103112928,"product_id":8098002796768,"position":8,"created_at":"2023-09-08T21:15:50+01:00","updated_at":"2023-09-08T23:02:26+01:00","alt":"Soft Pig Fluffy Pyjama 1-Piece Set | NEW - Kawaiies - Adorable - Cute - Plushies - Plush - Kawaii","width":766,"height":766,"src":"https:\/\/cdn.shopify.com\/s\/files\/1\/0306\/9794\/7272\/files\/S6aaeb81d307f473c89033c2768d8baa3l.jpg?v=1694210546","variant_ids":[]}],"image":{"id":39184102719712,"product_id":8098002796768,"position":1,"created_at":"2023-09-08T21:15:29+01:00","updated_at":"2023-09-08T21:15:31+01:00","alt":"Soft Pig Fluffy Pyjama 1-Piece Set | NEW - Kawaiies - Adorable - Cute - Plushies - Plush - Kawaii","width":800,"height":800,"src":"https:\/\/cdn.shopify.com\/s\/files\/1\/0306\/9794\/7272\/products\/S5f63fd6b60d74f10a7155edc33fe72bc1.jpg?v=1694204131","variant_ids":[44175170961632,44175170994400,44175171027168]}}}